spectroview/__init__.py
spectroview/main.py
spectroview/model/__init__.py
spectroview/model/m_file_converter.py
spectroview/model/m_fit_model_manager.py
spectroview/model/m_graph.py
spectroview/model/m_io.py
spectroview/model/m_settings.py
spectroview/model/m_spectra.py
spectroview/model/m_spectrum.py
spectroview/resources/SPECTROview_UserManual.pdf
spectroview/resources/__init__.py
spectroview/resources/plotpolicy.mplstyle
spectroview/resources/icons/2Dmap.png
spectroview/resources/icons/FileConvert.png
spectroview/resources/icons/Picture1.png
spectroview/resources/icons/about.png
spectroview/resources/icons/add.png
spectroview/resources/icons/bar.png
spectroview/resources/icons/baseline.png
spectroview/resources/icons/box.png
spectroview/resources/icons/clear.png
spectroview/resources/icons/close.png
spectroview/resources/icons/collect.png
spectroview/resources/icons/copy.png
spectroview/resources/icons/copy10.png
spectroview/resources/icons/copy3.png
spectroview/resources/icons/copy_label.png.png
spectroview/resources/icons/cut.png
spectroview/resources/icons/dark-light.png
spectroview/resources/icons/dark.png
spectroview/resources/icons/done.png
spectroview/resources/icons/edit.png
spectroview/resources/icons/filter.png
spectroview/resources/icons/fitting.png
spectroview/resources/icons/horizontal-line.png
spectroview/resources/icons/icon.png
spectroview/resources/icons/icons8-copy-96.png
spectroview/resources/icons/icons8-documents-folder-80.png
spectroview/resources/icons/icons8-documents-folder-96.png
spectroview/resources/icons/icons8-download-96.png
spectroview/resources/icons/icons8-folder-96.png
spectroview/resources/icons/icons8-graph-96.png
spectroview/resources/icons/icons8-open-document-96.png
spectroview/resources/icons/icons8-open-end-wrench-96.png
spectroview/resources/icons/icons8-remove-100.png
spectroview/resources/icons/icons8-save-all-48.png
spectroview/resources/icons/icons8-save-all-64.png
spectroview/resources/icons/icons8-trash-128.png
spectroview-26.2.1.dist-info/licenses/LICENSE
spectroview-26.2.1.dist-info/METADATA
spectroview-26.2.1.dist-info/WHEEL
spectroview-26.2.1.dist-info/entry_points.txt
spectroview-26.2.1.dist-info/top_level.txt
spectroview-26.2.1.dist-info/RECORD
