Metadata-Version: 2.4
Name: spectroview
Version: 26.2.1
Summary: SPECTROView: A Tool for Spectroscopic Data Processing and Visualization
Author-email: Van Hoan Le <van-hoan.le@cea.fr>
License:                     GNU GENERAL PUBLIC LICENSE
Project-URL: Homepage, https://github.com/CEA-MetroCarac/SPECTROview
Keywords: SPECTROview,fit,fitting,spectra,spectrum,spectroscopic,visualization,Raman,Photoluminescence,wafer-data,2D-maps,data-analysis,MVVM,PySide6,Qt,hyperspectral-imaging
Classifier: Development Status :: 4 - Beta
Classifier: Intended Audience :: Science/Research
Classifier: Topic :: Scientific/Engineering :: Physics
Classifier: Topic :: Scientific/Engineering :: Chemistry
Classifier: Topic :: Scientific/Engineering :: Visualization
Classifier: Programming Language :: Python :: 3
Classifier: Programming Language :: Python :: 3.8
Classifier: Programming Language :: Python :: 3.9
Classifier: Programming Language :: Python :: 3.10
Classifier: Programming Language :: Python :: 3.11
Classifier: Programming Language :: Python :: 3.12
Classifier: License :: OSI Approved :: GNU General Public License v3 (GPLv3)
Classifier: Operating System :: Microsoft :: Windows
Classifier: Operating System :: POSIX :: Linux
Classifier: Operating System :: MacOS :: MacOS X
Requires-Python: >=3.8
License-File: LICENSE
Requires-Dist: fitspy==2025.6
Requires-Dist: numpy
Requires-Dist: openpyxl
Requires-Dist: pandas
Requires-Dist: matplotlib==3.8.4
Requires-Dist: seaborn==0.13.2
Requires-Dist: pyside6
Requires-Dist: markdown
Requires-Dist: scipy
Requires-Dist: lmfit
Requires-Dist: pywin32; platform_system == "Windows"
Requires-Dist: superqt
Provides-Extra: dev
Requires-Dist: pytest; extra == "dev"
Requires-Dist: pytest-qt; extra == "dev"
Requires-Dist: black; extra == "dev"
Requires-Dist: flake8; extra == "dev"
Provides-Extra: test
Requires-Dist: pytest; extra == "test"
Requires-Dist: pytest-qt; extra == "test"
Dynamic: license-file
